{
    "assets": [
        {
            "id": "apathfinding",
            "stars": 36
        },
        {
            "id": "daabbcc",
            "stars": 42
        },
        {
            "id": "defold-tile-raycast",
            "stars": 4
        },
        {
            "id": "defoldapiforvisualstudiocode",
            "stars": 23
        },
        {
            "id": "modplayer",
            "stars": 6
        },
        {
            "id": "pcgrandom",
            "stars": 18
        },
        {
            "id": "tinyhttp",
            "stars": 0
        }
    ],
    "id": "6100d3b33dfe49f042484ab76af0781e",
    "name": "Selim Ana\u00e7"
}