{
  "assets": [
    {
      "id": "adinfo", 
      "stars": 0
    }, 
    {
      "id": "camera", 
      "stars": 4
    }, 
    {
      "id": "endlessrunner", 
      "stars": 99
    }, 
    {
      "id": "facebook", 
      "stars": 7
    }, 
    {
      "id": "facebookinstantgames", 
      "stars": 38
    }, 
    {
      "id": "googleanalyticsforfirebase", 
      "stars": 12
    }, 
    {
      "id": "googleplaygameservices", 
      "stars": 15
    }, 
    {
      "id": "iac", 
      "stars": 2
    }, 
    {
      "id": "iap", 
      "stars": 10
    }, 
    {
      "id": "magiclinker", 
      "stars": 99
    }, 
    {
      "id": "platformertutorial", 
      "stars": 7
    }, 
    {
      "id": "push", 
      "stars": 10
    }, 
    {
      "id": "siwa", 
      "stars": 2
    }, 
    {
      "id": "videoplayernative", 
      "stars": 5
    }
  ], 
  "id": "7a2340205545b175e20f44488bd30a49", 
  "name": "Defold"
}