{
    "assets": [
        {
            "id": "hypertrails",
            "stars": 41
        },
        {
            "id": "pointer-lock",
            "stars": 12
        },
        {
            "id": "reszip",
            "stars": 21
        },
        {
            "id": "scene3d",
            "stars": 94
        },
        {
            "id": "sentinel",
            "stars": 10
        },
        {
            "id": "sharpsprite",
            "stars": 26
        },
        {
            "id": "splitmix64",
            "stars": 12
        },
        {
            "id": "yagames",
            "stars": 34
        },
        {
            "id": "yametrica",
            "stars": 9
        }
    ],
    "id": "a0bfc7430b840873f242085ed47277c8",
    "name": "Indiesoft LLC"
}