{
    "assets": [
        {
            "id": "asset-store",
            "stars": 18
        },
        {
            "id": "crowd-runner-defold",
            "stars": 17
        },
        {
            "id": "decore",
            "stars": 12
        },
        {
            "id": "defold-event",
            "stars": 63
        },
        {
            "id": "defold-lang",
            "stars": 30
        },
        {
            "id": "defold-log",
            "stars": 31
        },
        {
            "id": "defold-parser",
            "stars": 9
        },
        {
            "id": "defold-proto",
            "stars": 13
        },
        {
            "id": "defold-quest",
            "stars": 9
        },
        {
            "id": "defold-saver",
            "stars": 42
        },
        {
            "id": "defold-token",
            "stars": 9
        },
        {
            "id": "defold-tweener",
            "stars": 55
        },
        {
            "id": "deployer",
            "stars": 43
        },
        {
            "id": "detiled",
            "stars": 4
        },
        {
            "id": "druid",
            "stars": 522
        },
        {
            "id": "panthera",
            "stars": 99
        },
        {
            "id": "panthera20",
            "stars": 99
        }
    ],
    "id": "fdec556e51a2ad846db08b8ba0ae3b86",
    "name": "Insality"
}