{
  "assets": [
    {
      "id": "defold-api-emmylua",
      "stars": 36,
      "timestamp": 1567163518.0
    },
    {
      "id": "defoldapiforsublimetext3",
      "stars": 8,
      "timestamp": 1567163518.0
    },
    {
      "id": "panthera",
      "stars": 54,
      "timestamp": 1669586732.0
    },
    {
      "id": "trenchbroom",
      "stars": 32,
      "timestamp": 1658219139.0
    },
    {
      "id": "vs-code-ide",
      "stars": 143,
      "timestamp": 1632134871.0
    }
  ],
  "id": "editor",
  "name": "Editor"
}