{
    "asset_url": "https://github.com/defold/asset-portal/blob/master/assets/dicebag.json",
    "author": "8BitSkull",
    "author_id": "f4ecd22ca7133c183d7f46be9c2d848b",
    "description": "A module of probability functions designed specifically for games.",
    "forum_url": "https://forum.defold.com/t/dicebag-probability-for-games/67169",
    "images": {
        "hero": "dicebag-hero.png",
        "thumb": "dicebag-thumb.png"
    },
    "library_url": "",
    "license": "CC0 1.0 Universal",
    "name": "Dicebag",
    "platforms": [
        "Android",
        "iOS",
        "macOS",
        "Windows",
        "Linux",
        "HTML5"
    ],
    "project_url": "https://github.com/8bitskull/dicebag",
    "stars": 25,
    "tags": [
        "Game mechanic",
        "Math",
        "Util"
    ],
    "timestamp": 1609787857.0,
    "website_url": ""
}