{
  "name": "Facebook Instant Games", 
  "license": "MIT License", 
  "author": "Defold", 
  "asset_url": "https://github.com/defold/awesome-defold/blob/master/assets/facebookinstantgames.json", 
  "library_url": "https://github.com/defold/extension-fbinstant/archive/master.zip", 
  "project_url": "https://github.com/defold/extension-fbinstant", 
  "platforms": [
    "HTML5"
  ], 
  "website_url": "", 
  "stars": 2, 
  "images": {
    "hero": "fbinstant.hero.jpg", 
    "thumb": "facebookinstantgames-thumb.png"
  }, 
  "id": "facebookinstantgames", 
  "tags": [
    "Extensions", 
    "Social"
  ], 
  "description": "Facebook Instant Games extension."
}