{
    "asset_url": "https://github.com/defold/asset-portal/blob/master/assets/i18n-defold.json",
    "author": "Chung Xa",
    "author_id": "b6cf80bbb897b02ad11260ccfb89e0a2",
    "description": "i18n for Defold",
    "forum_url": "",
    "github_url": "https://github.com/baochungit/i18n-defold",
    "images": {
        "hero": "i18n-defold-hero.png",
        "thumb": "i18n-defold-thumb.png"
    },
    "library_url": "https://github.com/baochungit/i18n-defold/archive/master.zip",
    "license": "MIT",
    "name": "i18n",
    "platforms": [
        "Android",
        "iOS",
        "macOS",
        "Windows",
        "Linux",
        "HTML5"
    ],
    "project_url": "https://github.com/baochungit/i18n-defold",
    "stars": 2,
    "tags": [
        "GUI",
        "Util"
    ],
    "timestamp": 1706082227.0,
    "website_url": ""
}