{"content":[{"name":"game.projectc","size":4024,"pieces":[{"name":"game0.projectc","offset":0}]},{"name":"game.arci","size":52848,"pieces":[{"name":"game0.arci","offset":0}]},{"name":"game.arcd","size":4253084,"pieces":[{"name":"game0.arcd","offset":0},{"name":"game1.arcd","offset":2097152},{"name":"game2.arcd","offset":4194304}]},{"name":"game.dmanifest","size":57932,"pieces":[{"name":"game0.dmanifest","offset":0}]},{"name":"game.public.der","size":162,"pieces":[{"name":"game0.public.der","offset":0}]}],"total_size":4368050}